[
    {
        "id": 1,
        "name": "경복궁",
        "reason": "조선 왕조의 법궁, 역사 탐방",
        "lat": 37.5796,
        "lng": 126.9770
    },
    {
        "id": 2,
        "name": "국립서울현충원",
        "reason": "순국선열의 얼을 기리는 역사적 장소",
        "lat": 37.5024,
        "lng": 126.9735
    },
    {
        "id": 3,
        "name": "북촌 한옥마을(야외 방탈출)",
        "reason": "전통 한옥의 정취와 함께하는 이색 체험",
        "lat": 37.5826,
        "lng": 126.9850
    },
    {
        "id": 4,
        "name": "DDP (동대문디자인플라자)",
        "reason": "현대적인 건축미와 전시 관람",
        "lat": 37.5665,
        "lng": 127.0090
    },
    {
        "id": 5,
        "name": "서울식물원",
        "reason": "도심 속 거대한 온실 정원",
        "lat": 37.5696,
        "lng": 126.8354
    },
    {
        "id": 6,
        "name": "서울숲",
        "reason": "도심 속 힐링과 피크닉",
        "lat": 37.5444,
        "lng": 127.0374
    },
    {
        "id": 7,
        "name": "통인시장",
        "reason": "엽전 도시락과 기름떡볶이 체험",
        "lat": 37.5808,
        "lng": 126.9707
    }
]